{
  "project_info": {
    "project_number": "213406424824",
    "project_id": "jobsfinderapp-a4713",
    "storage_bucket": "jobsfinderapp-a4713.appspot.com"
  },
  "client": [
    {
      "client_info": {
        "mobilesdk_app_id": "1:213406424824:android:2c4b4903d2404959d8e50d",
        "android_client_info": {
          "package_name": "com.joohnq.jobsfinderapp"
        }
      },
      "oauth_client": [],
      "api_key": [
        {
          "current_key": "AIzaSyCNY7PPGqVtK2UIg_ENl1MUoifuzwx9Fk0"
        }
      ],
      "services": {
        "appinvite_service": {
          "other_platform_oauth_client": []
        }
      }
    }
  ],
  "configuration_version": "1"
}